py_cylinder_fitting/__init__.py
py_cylinder_fitting/_coordinate_transformations.py
py_cylinder_fitting/best_fit_cylinder.py
py_cylinder_fitting-1.0.0.dist-info/LICENSE
py_cylinder_fitting-1.0.0.dist-info/METADATA
py_cylinder_fitting-1.0.0.dist-info/WHEEL
py_cylinder_fitting-1.0.0.dist-info/top_level.txt
py_cylinder_fitting-1.0.0.dist-info/RECORD
