Metadata-Version: 2.1
Name: py-cylinder-fitting
Version: 1.0.0
Summary: This package allows to compute the best fit cylinder given points in three-dimensional space.
Author-email: Cristiano Pizzamiglio <cristianopizzamiglio@gmail.com>
License: 
Project-URL: Homepage, https://github.com/CristianoPizzamiglio/py-cylinder-fitting
Keywords: cylinder,best-fit
Classifier: Programming Language :: Python :: 3
Classifier: License :: OSI Approved :: BSD License
Classifier: Operating System :: OS Independent
Requires-Python: >=3.7
License-File: LICENSE
Requires-Dist: scikit-spatial (>=1.0.1)
Requires-Dist: scipy (>=1.9.3)
